gkg_laser/__init__.py
gkg_laser/example.py
gkg_laser/laser_client.py
gkg_laser/laser_command.py
gkg_laser/laser_controller.py
gkg_laser-1.0.0.dist-info/METADATA
gkg_laser-1.0.0.dist-info/WHEEL
gkg_laser-1.0.0.dist-info/RECORD
