Metadata-Version: 2.3
Name: gkg-laser
Version: 1.0.0
Summary: 大族激光控制
Author: LiuWei
Author-email: 183074632@qq.com
Requires-Python: >=3.11
Classifier: Programming Language :: Python :: 3
Classifier: Programming Language :: Python :: 3.11
Classifier: Programming Language :: Python :: 3.12
Classifier: Programming Language :: Python :: 3.13
